<?xml version="1.0" encoding="UTF-8" ?>
{{CUT({{GET(noItems)}})}}{{
{{SET(noItems:true)}}
{{XML()}}{{
<document>
  <head>
    <style>
      .showTextOnHighlight {
      tv-text-highlight-style: marquee-on-highlight;
      }
      .rounded {
      itml-img-treatment: corner-small;
      }
      .hero {
      margin: -323 -280 0 0;
      }
      .header {
      .text-align: left;
      .margin: 0 0 0 -200;
      }
      .sectionLabel {
      text-align: center;
      <!--margin: 0 0 15 0;-->
      <!--color: #605e58;-->
      }
      .lightBackgroundColor {
      background-color: #efece6;
      }
      .darkBackgroundColor {
      background-color: #333333;
      }
    </style>
  </head>
  <stackTemplate theme="light" class="lightBackgroundColor">
    <identityBanner>
      <title class="header">Shelves</title>
      <subtitle class="header"><![CDATA[{{PMSVAL(name)}}    ]]></subtitle>
      <row>
        <buttonLockup onSelect="Presenter.load('Library','{{PMSID()}}','');">
          <badge src="{{RESOURCEURL(TVMLTemplates/Quartz2/images/buttons:Library:png)}}" width="50" height="50"/>
          <title>Sections</title>
        </buttonLockup>
        <buttonLockup onSelect="Presenter.load('Search', '{{PMSID()}}', '/search?query')">
          <badge src="{{RESOURCEURL(TVMLTemplates/Quartz2/images/buttons:Search:png)}}" width="50" height="50"/>
          <title>Search</title>
        </buttonLockup>
        <buttonLockup onSelect="Presenter.loadAndSwap('All_Servers_MenuBar', '{{PMSID()}}', '{{PATH()}}')">
          <badge src="{{RESOURCEURL(TVMLTemplates/Quartz2/images/buttons:Reload:png)}}" width="50" height="50"/>
          <title>Reload</title>
        </buttonLockup>
      </row>
    </identityBanner>
    {{XML(/hubs?excludeFields=summary)}}{{
    {{IFNODE(MediaContainer/Hub)}}{{
    {{SET(noItems:false)}}
    <collectionList>
      {{COPY(MediaContainer/Hub)}}{{
      {{IF({{CHK("{{VAL(size)}}">"0")}})}}{{
      <shelf id="{{VAL(hubIdentifier)}}">
        <header>
          <title><![CDATA[{{VAL(title)}}]]></title>
        </header>
        <section>
          {{IFNODE(Video)}}{{
          {{COPY(Video)}}{{
          
          {{IF({{CHK("{{VAL(type)}}"="movie")}})}}{{
          {{IF({{VAL(viewOffset)}})}}{{
          <lockup onSelect="Presenter.load('Movie_PrePlay', '{{PMSID()}}', '{{PATH({{VAL(key)}})}}')"
            onPlay="Presenter.loadContext('Videos_ResumePopUp', '{{PMSID()}}', '{{PATH({{VAL(key)}})}}')"
            onHoldSelect="Presenter.loadContext('Movie_MorePopUp', '{{PMSID()}}', '{{VAL(ratingKey)}}')">
            <img src="{{IMAGE_T(thumb::360)}}" height="375" width="250" />
            <overlay>
							<img style="tv-position: top-right; margin: -36 -30 120 120" src="{{RESOURCEURL(TVMLTemplates/Quartz2/images/flags:watching:png)}}"  width="72" height="72" />
						</overlay>
						<title class="showTextOnHighlight"><![CDATA[{{VAL(title)}}]]></title>
            <subtitle><![CDATA[{{VAL(year)}}]]></subtitle>
          </lockup>
          }}
          {{IF(!{{VAL(viewOffset)}})}}{{
          <lockup onSelect="Presenter.load('Movie_PrePlay', '{{PMSID()}}', '{{PATH({{VAL(key)}})}}')"
            onPlay="videoPlayer.play('{{PMSID()}}', '{{PATH({{VAL(key)}})}}')"
            onHoldSelect="Presenter.loadContext('Movie_MorePopUp', '{{PMSID()}}', '{{VAL(ratingKey)}}')">
            <img src="{{IMAGE_T(thumb::360)}}" height="375" width="250" />
            {{IF(!{{VAL(viewCount)}})}}{{
						<overlay>
							<img style="tv-position: top-right; margin: -36 -30 120 120" src="{{RESOURCEURL(TVMLTemplates/Quartz2/images/flags:unwatched:png)}}"  width="72" height="72" />
						</overlay>
						}}
            <title class="showTextOnHighlight"><![CDATA[{{VAL(title)}}]]></title>
            <subtitle><![CDATA[{{VAL(year)}}]]></subtitle>
          </lockup>
          }}
          }}
          
          {{IF({{CHK("{{VAL(type)}}"="episode")}})}}{{
          <lockup onSelect="Presenter.load('TVShow_PrePlay', '{{PMSID()}}', '{{PATH({{VAL(key)}})}}')"
          onHoldSelect="Presenter.loadContext('Movie_MorePopUp', '{{PMSID()}}', '{{VAL(ratingKey)}}')"
          {{IF(!{{VAL(viewOffset)}})}}{{ 
          onPlay="videoPlayer.play('{{PMSID()}}', '{{PATH({{VAL(key)}})}}')"
          }}
          {{IF({{VAL(viewOffset)}})}}{{ 
          onPlay="Presenter.loadContext('Videos_ResumePopUp', '{{PMSID()}}', '{{PATH({{VAL(key)}})}}')"
          }}
          >
            <img src="{{IMAGE_T(grandparentThumb::360)}}" height="375" width="250" />
            <overlay>
            	{{IF({{VAL(viewOffset)}})}}{{
              <img style="tv-position: top-right; margin: -36 -30 120 120" src="{{RESOURCEURL(TVMLTemplates/Quartz2/images/flags:watching:png)}}"  width="72" height="72" />
            	}}
            	{{IF(!{{VAL(viewOffset)}})}}{{
            	{{IF(!{{VAL(viewCount)}})}}{{
              <img style="tv-position: top-right; margin: -36 -30 120 120" src="{{RESOURCEURL(TVMLTemplates/Quartz2/images/flags:unwatched:png)}}"  width="72" height="72" />
            	}}
            	}}
            </overlay>
            <title><![CDATA[{{VAL(title)}}]]></title>
            <subtitle>{{EP_INDEX({{VAL(parentIndex:)}}:{{VAL(index:)}})}}</subtitle>
          </lockup>
          }}
          
          }}
          }}
          
          {{IFNODE(Directory)}}{{
          {{COPY(Directory)}}{{
          {{IF({{CHK("{{VAL(type)}}"="season")}})}}{{
          <lockup onSelect="Presenter.load('TVShow_SeasonList', '{{PMSID()}}', '{{PATH({{VAL(key)}})}}')"
            onPlay="videoPlayer.play('{{PMSID()}}', '{{PATH({{VAL(key)}})}}')"
            onHoldSelect="Presenter.loadContext('Movie_MorePopUp', '{{PMSID()}}', '{{VAL(ratingKey)}}')">
            <img src="{{IMAGE_T(thumb::360)}}" height="375" width="250" />
            {{IF(!{{CHK("{{VAL(leafCount)}}"="{{VAL(viewedLeafCount)}}")}})}}{{
            <overlay>
            	<img style="tv-position: top-right; margin: -36 -30 120 120" src="{{RESOURCEURL(TVMLTemplates/Quartz2/images/flags:unwatched:png)}}"  width="72" height="72" />
            	<decorationLabel class="count">{{EVAL({{VAL(leafCount)}}-{{VAL(viewedLeafCount)}})}}</decorationLabel>
            </overlay>	
            }}
            <title><![CDATA[{{VAL(title)}}]]></title>
            <subtitle><![CDATA[ ]]></subtitle>
          </lockup>
          }}
          {{IF({{CHK("{{VAL(type)}}"="album")}})}}{{
          <lockup onSelect="Presenter.load('Music_Album', '{{PMSID()}}', '{{PATH({{VAL(key)}})}}')"
            onPlay="audioPlayer.play('{{PMSID()}}', '{{PATH({{VAL(key)}})}}')">
            <img src="{{IMAGE_T(thumb::360)}}" height="308" width="308" />
            <title class="showTextOnHighlight"><![CDATA[{{VAL(title)}}]]></title>
            <subtitle><![CDATA[{{VAL(year)}}]]></subtitle>
          </lockup>
          }}
          }}
          }}
          
          {{IFNODE(Photo)}}{{
          {{COPY(Photo)}}{{
          <lockup onSelect="photoPresenter.slideshow('{{PMSID()}}', '{{VAL(key)}}')"
                        onPlay="photoPresenter.slideshow('{{PMSID()}}', '{{VAL(key)}}')"
                        onSelectHold="ScrobbleMenu">
                        <img src="{{IMAGE_T(thumb::360)}}" height="308" width="308" />
                        <title class="showTextOnHighlight"><![CDATA[{{VAL(originallyAvailableAt)}}]]></title>
                        
                    </lockup>
          }}
          }}
        </section>
      </shelf>
      }}
      }}
    }}
    }}
    </collectionList>
  </stackTemplate>
</document>
}}
}}

{{IF({{GET(noItems)}})}}{{  <!--enable if no items added-->
<document>
  <alertTemplate>
    <title>TITLE</title>
    <description>{{TEXT(Plex Media Server: No Items Available)}}</description>
  </alertTemplate>
</document>
}}

